{
    "image_path": "augmented/processed_other_20250504_g22a8nyg_aug1.png",
    "image_width": 489,
    "image_height": 1024,
    "regions": {
        "store_name": [
            0,
            0,
            489,
            204
        ],
        "coupon_code": [
            48,
            409,
            440,
            614
        ],
        "expiry_date": [
            0,
            819,
            489,
            1024
        ],
        "description": [
            342,
            614,
            440,
            716
        ],
        "amount": [
            48,
            614,
            440,
            819
        ]
    }
}